py_ocr/__init__.py
py_ocr/cli.py
py_ocr/ocr_processor.py
pdf_searchable_ocr-0.1.1.dist-info/METADATA
pdf_searchable_ocr-0.1.1.dist-info/WHEEL
pdf_searchable_ocr-0.1.1.dist-info/entry_points.txt
pdf_searchable_ocr-0.1.1.dist-info/licenses/LICENSE
pdf_searchable_ocr-0.1.1.dist-info/RECORD
