Metadata-Version: 2.4
Name: pdf-searchable-ocr
Version: 0.1.1
Summary: A simple Python package for OCR with searchable PDF generation using PaddleOCR
Project-URL: Homepage, https://github.com/jasminmistry/pdf-searchable-ocr
Project-URL: Repository, https://github.com/jasminmistry/pdf-searchable-ocr.git
Project-URL: Documentation, https://github.com/jasminmistry/pdf-searchable-ocr#readme
Project-URL: Bug Tracker, https://github.com/jasminmistry/pdf-searchable-ocr/issues
Author-email: Jasmin Mistry <mistry.jasmin@gmail.com>
Maintainer-email: Jasmin Mistry <mistry.jasmin@gmail.com>
License: MIT
License-File: LICENSE
Keywords: computer-vision,ocr,paddleocr,pdf,searchable-pdf,text-recognition
Classifier: Development Status :: 4 - Beta
Classifier: Intended Audience :: Developers
Classifier: Intended Audience :: Science/Research
Classifier: License :: OSI Approved :: MIT License
Classifier: Operating System :: OS Independent
Classifier: Programming Language :: Python :: 3
Classifier: Programming Language :: Python :: 3.8
Classifier: Programming Language :: Python :: 3.9
Classifier: Programming Language :: Python :: 3.10
Classifier: Programming Language :: Python :: 3.11
Classifier: Programming Language :: Python :: 3.12
Classifier: Topic :: Multimedia :: Graphics :: Capture :: Digital Camera
Classifier: Topic :: Scientific/Engineering :: Image Recognition
Classifier: Topic :: Software Development :: Libraries :: Python Modules
Classifier: Topic :: Text Processing
Requires-Python: >=3.8
Requires-Dist: opencv-python>=4.0.0
Requires-Dist: paddleocr>=2.7.0
Requires-Dist: paddlepaddle>=2.5.0
Requires-Dist: pillow>=8.0.0
Requires-Dist: reportlab>=4.0.0
Provides-Extra: dev
Requires-Dist: black>=22.0.0; extra == 'dev'
Requires-Dist: flake8>=5.0.0; extra == 'dev'
Requires-Dist: isort>=5.0.0; extra == 'dev'
Requires-Dist: mypy>=1.0.0; extra == 'dev'
Requires-Dist: pytest>=7.0.0; extra == 'dev'
Provides-Extra: gpu
Requires-Dist: paddlepaddle-gpu>=2.5.0; extra == 'gpu'
